cff_from_621/__init__.py
cff_from_621/cli.py
cff_from_621/lib.py
cff_from_621/version.py
cff_from_621-0.1.dist-info/METADATA
cff_from_621-0.1.dist-info/WHEEL
cff_from_621-0.1.dist-info/entry_points.txt
cff_from_621-0.1.dist-info/top_level.txt
cff_from_621-0.1.dist-info/RECORD
