Metadata-Version: 2.1
Name: cff-from-621
Version: 0.1
Summary: Generates metadata in the Citation File Format for Python projects from their PEP-621 compliant package definition. Includes a CLI. 
Author: Frank Sachsenheim
Project-URL: Homepage, https://pypi.org/project/cff-from-621/
Project-URL: Repository, https://github.com/delb-xml/cff-from-621
Project-URL: Issue tracker, https://github.com/delb-xml/cff-from-621/issues
Keywords: PEP-621,CFF,conversion
Classifier: Development Status :: 4 - Beta
Classifier: Environment :: Console
Classifier: Intended Audience :: Developers
Classifier: Intended Audience :: Science/Research
Classifier: License :: OSI Approved :: GNU General Public License v3 (GPLv3)
Classifier: Natural Language :: English
Classifier: Operating System :: OS Independent
Classifier: Programming Language :: Python :: 3
Classifier: Topic :: Software Development
Requires-Python: >=3.10
Requires-Dist: cffconvert ~=2.0
Requires-Dist: PyYAML
Requires-Dist: tomli ; python_version < "3.11"
Provides-Extra: development
Requires-Dist: build ; extra == 'development'
Requires-Dist: flake8-black ; extra == 'development'
Requires-Dist: mypy ; extra == 'development'
Requires-Dist: pytest ; extra == 'development'
Requires-Dist: types-PyYAML ; extra == 'development'
